nnrf/__init__.py
nnrf/_des_knn.py
nnrf/_nn.py
nnrf/_nndt.py
nnrf/_nnrf.py
nnrf/analysis/__init__.py
nnrf/analysis/_confusion_matrix.py
nnrf/analysis/_report.py
nnrf/analysis/metrics.py
nnrf/ml/__init__.py
nnrf/ml/activation.py
nnrf/ml/loss.py
nnrf/ml/optimizer.py
nnrf/ml/regularizer.py
nnrf/utils/__init__.py
nnrf/utils/_base.py
nnrf/utils/_batch_dataset.py
nnrf/utils/_check.py
nnrf/utils/_estimator.py
nnrf/utils/_misc.py
tests/__init__.py
tests/test_des.py
tests/test_nn.py
tests/test_nndt.py
tests/test_nnrf.py
tests/test_scaffold.py
nnrf-0.9.0.dist-info/LICENSE
nnrf-0.9.0.dist-info/METADATA
nnrf-0.9.0.dist-info/WHEEL
nnrf-0.9.0.dist-info/top_level.txt
nnrf-0.9.0.dist-info/zip-safe
nnrf-0.9.0.dist-info/RECORD
