Metadata-Version: 2.1
Name: nnrf
Version: 0.9.0
Summary: Neural Network with Random Forest Structure
Home-page: http://github.com/paradoxysm/nnrf
Author: paradoxysm
Author-email: paradoxysm.dev@gmail.com
License: BSD-3-Clause
Download-URL: https://github.com/paradoxysm/nnrf/archive/0.9.0.tar.gz
Keywords: python,ml,neural-network,random-forest
Platform: UNKNOWN
Classifier: Development Status :: 4 - Beta
Classifier: Intended Audience :: Developers
Classifier: Natural Language :: English
Classifier: License :: OSI Approved :: BSD License
Classifier: Operating System :: OS Independent
Classifier: Programming Language :: Python
Classifier: Programming Language :: Python :: 3
Classifier: Programming Language :: Python :: 3.4
Classifier: Programming Language :: Python :: 3.5
Classifier: Programming Language :: Python :: 3.6
Classifier: Programming Language :: Python :: 3.7
Classifier: Topic :: Software Development :: Libraries :: Python Modules
Classifier: Topic :: Scientific/Engineering :: Artificial Intelligence
Classifier: Topic :: Scientific/Engineering :: Information Analysis
Classifier: Intended Audience :: Science/Research
Requires-Python: >=3.4, <4
Requires-Dist: numpy
Requires-Dist: tqdm
Requires-Dist: sklearn
